access2base/__init__.pyi
access2base/py.typed
types_access2base-1.0.2.dist-info/LICENSE
types_access2base-1.0.2.dist-info/METADATA
types_access2base-1.0.2.dist-info/WHEEL
types_access2base-1.0.2.dist-info/top_level.txt
types_access2base-1.0.2.dist-info/RECORD
